virtual/__init__.py
virtual/RandomCharGen/__init__.py
virtual/RandomCharGen/randCharMain.py
RandomPyCharGen-0.0.1.dist-info/METADATA
RandomPyCharGen-0.0.1.dist-info/WHEEL
RandomPyCharGen-0.0.1.dist-info/top_level.txt
RandomPyCharGen-0.0.1.dist-info/RECORD
