Metadata-Version: 2.1
Name: RandomPyCharGen
Version: 0.0.1
Summary: A simple python program that creates a string of random characters and places them into a data collection of your choice. 
Home-page: https://github.com/borkusgod
Author: William Bourque
Author-email: 
License: LPGL
Platform: UNKNOWN
